<?xml version="1.0" encoding="UTF-8" ?>
<persistence xmlns:xsi="http://www.w3.org/2001/XMLSchema-instance" xsi:schemaLocation="http://xmlns.jcp.org/xml/ns/persistence http://xmlns.jcp.org/xml/ns/persistence/persistence_2_2.xsd" version="2.2" xmlns="http://java.sun.com/xml/ns/persistence">
	<persistence-unit name="app" transaction-type="RESOURCE_LOCAL">
		<provider>org.eclipse.persistence.jpa.PersistenceProvider</provider>
		<non-jta-data-source>java:comp/env/jdbc/atlas</non-jta-data-source>
		<shared-cache-mode>ENABLE_SELECTIVE</shared-cache-mode>

		<!-- attribute converters -->
		<class>com.kidscademy.atlas.studio.dao.FileConverter</class>
		<class>com.kidscademy.atlas.studio.dao.UrlConverter</class>

		<!-- embeddables -->
		<class>com.kidscademy.atlas.studio.model.Feature</class>
		<class>com.kidscademy.atlas.studio.model.Link</class>
		<class>com.kidscademy.atlas.studio.model.HDate</class>
		<class>com.kidscademy.atlas.studio.model.Region</class>

		<!-- entities -->
		<class>com.kidscademy.atlas.studio.model.User</class>
		<class>com.kidscademy.atlas.studio.model.AtlasCollection</class>
		<class>com.kidscademy.atlas.studio.model.AtlasObject</class>
		<class>com.kidscademy.atlas.studio.model.AtlasItem</class>
		<class>com.kidscademy.atlas.studio.model.AtlasImages</class>
		<class>com.kidscademy.atlas.studio.model.AtlasRelated</class>
		<class>com.kidscademy.atlas.studio.model.AtlasLinks</class>
		<class>com.kidscademy.atlas.studio.model.Image</class>
		<class>com.kidscademy.atlas.studio.model.MediaFile</class>

		<class>com.kidscademy.atlas.studio.model.FeatureMeta</class>
		<class>com.kidscademy.atlas.studio.model.LinkMeta</class>

		<class>com.kidscademy.atlas.studio.export.ExportItem</class>

		<class>com.kidscademy.atlas.studio.model.Release</class>
		<class>com.kidscademy.atlas.studio.model.ReleaseItem</class>
		<class>com.kidscademy.atlas.studio.model.ReleaseParent</class>
		<class>com.kidscademy.atlas.studio.model.ReleaseChild</class>

		<properties>
			<property name="eclipselink.logging.level.sql" value="FINE" />
		</properties>
	</persistence-unit>

	<persistence-unit name="itis" transaction-type="RESOURCE_LOCAL">
		<provider>org.eclipse.persistence.jpa.PersistenceProvider</provider>
		<non-jta-data-source>java:comp/env/jdbc/itis</non-jta-data-source>
	</persistence-unit>

	<persistence-unit name="import" transaction-type="RESOURCE_LOCAL">
		<shared-cache-mode>ALL</shared-cache-mode>

		<class>com.kidscademy.atlas.studio.dao.UrlConverter</class>

		<class>com.kidscademy.atlas.studio.model.Feature</class>
		<class>com.kidscademy.atlas.studio.model.Link</class>
		<class>com.kidscademy.atlas.studio.model.HDate</class>
		<class>com.kidscademy.atlas.studio.model.Region</class>

		<class>com.kidscademy.atlas.studio.model.User</class>
		<class>com.kidscademy.atlas.studio.model.AtlasCollection</class>
		<class>com.kidscademy.atlas.studio.model.AtlasObject</class>
		<class>com.kidscademy.atlas.studio.model.AtlasItem</class>
		<class>com.kidscademy.atlas.studio.model.Image</class>
		<class>com.kidscademy.atlas.studio.model.MediaFile</class>

		<class>com.kidscademy.atlas.studio.export.ExportItem</class>

		<properties>
			<property name="javax.persistence.jdbc.driver" value="com.mysql.jdbc.Driver" />
			<property name="javax.persistence.jdbc.url" value="jdbc:mysql://localhost:3306/atlas" />
			<property name="javax.persistence.jdbc.user" value="kids_cademy" />
			<property name="javax.persistence.jdbc.password" value="kids_cademy" />
			<property name="javax.persistence.jdbc.show_sql" value="true" />

			<property name="eclipselink.logging.level.sql" value="FINE" />
		</properties>
	</persistence-unit>

	<persistence-unit name="test" transaction-type="RESOURCE_LOCAL">
		<!-- disable cache on tests since create dependencies between test cases -->
		<shared-cache-mode>NONE</shared-cache-mode>

		<class>com.kidscademy.atlas.studio.dao.FileConverter</class>
		<class>com.kidscademy.atlas.studio.dao.UrlConverter</class>

		<class>com.kidscademy.atlas.studio.model.Feature</class>
		<class>com.kidscademy.atlas.studio.model.Link</class>
		<class>com.kidscademy.atlas.studio.model.HDate</class>
		<class>com.kidscademy.atlas.studio.model.Region</class>

		<class>com.kidscademy.atlas.studio.model.User</class>
		<class>com.kidscademy.atlas.studio.model.AtlasCollection</class>
		<class>com.kidscademy.atlas.studio.model.AtlasObject</class>
		<class>com.kidscademy.atlas.studio.model.AtlasItem</class>
		<class>com.kidscademy.atlas.studio.model.Image</class>
		<class>com.kidscademy.atlas.studio.model.MediaFile</class>

		<class>com.kidscademy.atlas.studio.model.FeatureMeta</class>
		<class>com.kidscademy.atlas.studio.model.LinkMeta</class>

		<class>com.kidscademy.atlas.studio.export.ExportItem</class>

		<class>com.kidscademy.atlas.studio.model.Release</class>
		<class>com.kidscademy.atlas.studio.model.ReleaseItem</class>
		<class>com.kidscademy.atlas.studio.model.ReleaseParent</class>
		<class>com.kidscademy.atlas.studio.model.ReleaseChild</class>

		<properties>
			<property name="javax.persistence.jdbc.driver" value="com.mysql.jdbc.Driver" />
			<property name="javax.persistence.jdbc.url" value="jdbc:mysql://localhost:3306/atlas_test" />
			<property name="javax.persistence.jdbc.user" value="kids_cademy" />
			<property name="javax.persistence.jdbc.password" value="kids_cademy" />
			<property name="javax.persistence.jdbc.show_sql" value="true" />

			<property name="eclipselink.logging.level.sql" value="FINE" />
		</properties>
	</persistence-unit>

	<persistence-unit name="itis-test" transaction-type="RESOURCE_LOCAL">
		<shared-cache-mode>NONE</shared-cache-mode>

		<properties>
			<property name="javax.persistence.jdbc.driver" value="com.mysql.jdbc.Driver" />
			<property name="javax.persistence.jdbc.url" value="jdbc:mysql://localhost:3306/itis" />
			<property name="javax.persistence.jdbc.user" value="kids_cademy" />
			<property name="javax.persistence.jdbc.password" value="kids_cademy" />

			<property name="eclipselink.logging.level.sql" value="FINE" />
		</properties>
	</persistence-unit>

	<persistence-unit name="api" transaction-type="RESOURCE_LOCAL">
		<shared-cache-mode>NONE</shared-cache-mode>

		<class>com.kidscademy.atlas.studio.api.Parent</class>

		<properties>
			<property name="javax.persistence.jdbc.driver" value="com.mysql.jdbc.Driver" />
			<property name="javax.persistence.jdbc.url" value="jdbc:mysql://localhost:3306/kids_cademy_poc" />
			<property name="javax.persistence.jdbc.user" value="kids_cademy" />
			<property name="javax.persistence.jdbc.password" value="kids_cademy" />

			<property name="eclipselink.logging.level.sql" value="FINE" />
		</properties>
	</persistence-unit>

</persistence>
